bip39_mnemonic_decrypt/__init__.py
bip39_mnemonic_decrypt-1.0.0.dist-info/METADATA
bip39_mnemonic_decrypt-1.0.0.dist-info/WHEEL
bip39_mnemonic_decrypt-1.0.0.dist-info/top_level.txt
bip39_mnemonic_decrypt-1.0.0.dist-info/RECORD
