Metadata-Version: 2.1
Name: bip39_mnemonic_decrypt
Version: 1.0.0
Summary: Decrypts jsBIP39 data.
Home-page: https://example.com
Author: James
Author-email: james@coding.com
Project-URL: Docs, https://docs.example.com
Classifier: Programming Language :: Python :: 3
Classifier: License :: OSI Approved :: MIT License
Classifier: Operating System :: OS Independent
Requires-Python: >=3.6
